majora/__init__.py
majora/majora.py
majora-0.0.3.dist-info/METADATA
majora-0.0.3.dist-info/WHEEL
majora-0.0.3.dist-info/top_level.txt
majora-0.0.3.dist-info/RECORD
