Metadata-Version: 2.1
Name: majora
Version: 0.0.3
Summary: Majora is a python library that automates common tasks in your exploratory data analysis. 
Home-page: https://github.com/GrandPurpleOcelot/Auto-EDA
Author: Thien Nghiem
Author-email: thien.nghiem94@gmail.com
License: UNKNOWN
Platform: UNKNOWN
Classifier: Programming Language :: Python :: 3
Classifier: License :: OSI Approved :: MIT License
Classifier: Operating System :: OS Independent
Requires-Python: >=3.6
Requires-Dist: appnope (==0.1.0)
Requires-Dist: astroid (==2.4.2)
Requires-Dist: attrs (==19.3.0)
Requires-Dist: backcall (==0.2.0)
Requires-Dist: bleach (==3.1.5)
Requires-Dist: Brotli (==1.0.7)
Requires-Dist: certifi (==2020.4.5.2)
Requires-Dist: click (==7.1.2)
Requires-Dist: colour (==0.1.5)
Requires-Dist: cycler (==0.10.0)
Requires-Dist: decorator (==4.4.2)
Requires-Dist: defusedxml (==0.6.0)
Requires-Dist: dtreeviz (==0.8.2)
Requires-Dist: entrypoints (==0.3)
Requires-Dist: future (==0.18.2)
Requires-Dist: graphviz (==0.14)
Requires-Dist: importlib-metadata (==1.6.1)
Requires-Dist: ipykernel (==5.3.0)
Requires-Dist: ipython (==7.15.0)
Requires-Dist: ipython-genutils (==0.2.0)
Requires-Dist: isort (==4.3.21)
Requires-Dist: itsdangerous (==1.1.0)
Requires-Dist: jedi (==0.17.0)
Requires-Dist: Jinja2 (==2.11.2)
Requires-Dist: joblib (==0.15.1)
Requires-Dist: jsonschema (==3.2.0)
Requires-Dist: jupyter-client (==6.1.3)
Requires-Dist: jupyter-core (==4.6.3)
Requires-Dist: kiwisolver (==1.2.0)
Requires-Dist: lazy-object-proxy (==1.4.3)
Requires-Dist: MarkupSafe (==1.1.1)
Requires-Dist: matplotlib (==3.2.1)
Requires-Dist: mccabe (==0.6.1)
Requires-Dist: missingno (==0.4.2)
Requires-Dist: mistune (==0.8.4)
Requires-Dist: nbconvert (==5.6.1)
Requires-Dist: nbformat (==5.0.7)
Requires-Dist: notebook (==6.0.3)
Requires-Dist: numpy (==1.18.5)
Requires-Dist: packaging (==20.4)
Requires-Dist: pandas (==1.0.4)
Requires-Dist: pandocfilters (==1.4.2)
Requires-Dist: parso (==0.7.0)
Requires-Dist: pexpect (==4.8.0)
Requires-Dist: pickleshare (==0.7.5)
Requires-Dist: plotly (==4.8.2)
Requires-Dist: prince (==0.7.0)
Requires-Dist: prometheus-client (==0.8.0)
Requires-Dist: prompt-toolkit (==3.0.5)
Requires-Dist: ptyprocess (==0.6.0)
Requires-Dist: Pygments (==2.6.1)
Requires-Dist: pylint (==2.5.3)
Requires-Dist: pyparsing (==2.4.7)
Requires-Dist: pyrsistent (==0.16.0)
Requires-Dist: python-dateutil (==2.8.1)
Requires-Dist: pytz (==2020.1)
Requires-Dist: pyzmq (==18.1.1)
Requires-Dist: retrying (==1.3.3)
Requires-Dist: scikit-learn (==0.23.1)
Requires-Dist: scipy (==1.4.1)
Requires-Dist: seaborn (==0.10.1)
Requires-Dist: Send2Trash (==1.5.0)
Requires-Dist: six (==1.15.0)
Requires-Dist: sklearn (==0.0)
Requires-Dist: terminado (==0.8.3)
Requires-Dist: testpath (==0.4.4)
Requires-Dist: threadpoolctl (==2.1.0)
Requires-Dist: toml (==0.10.1)
Requires-Dist: tornado (==6.0.4)
Requires-Dist: traitlets (==4.3.3)
Requires-Dist: typed-ast (==1.4.1)
Requires-Dist: wcwidth (==0.2.4)
Requires-Dist: webencodings (==0.5.1)
Requires-Dist: Werkzeug (==1.0.1)
Requires-Dist: wrapt (==1.12.1)
Requires-Dist: zipp (==3.1.0)
